{
    "0": {
        "precision": 1.0,
        "recall": 1.0,
        "f1-score": 1.0,
        "support": 18.0
    },
    "1": {
        "precision": 1.0,
        "recall": 1.0,
        "f1-score": 1.0,
        "support": 20.0
    },
    "2": {
        "precision": 1.0,
        "recall": 0.95,
        "f1-score": 0.9743589743589743,
        "support": 20.0
    },
    "3": {
        "precision": 1.0,
        "recall": 1.0,
        "f1-score": 1.0,
        "support": 18.0
    },
    "4": {
        "precision": 1.0,
        "recall": 1.0,
        "f1-score": 1.0,
        "support": 20.0
    },
    "5": {
        "precision": 1.0,
        "recall": 1.0,
        "f1-score": 1.0,
        "support": 20.0
    },
    "6": {
        "precision": 0.9523809523809523,
        "recall": 1.0,
        "f1-score": 0.975609756097561,
        "support": 20.0
    },
    "7": {
        "precision": 1.0,
        "recall": 1.0,
        "f1-score": 1.0,
        "support": 7.0
    },
    "8": {
        "precision": 0.9523809523809523,
        "recall": 1.0,
        "f1-score": 0.975609756097561,
        "support": 20.0
    },
    "9": {
        "precision": 1.0,
        "recall": 1.0,
        "f1-score": 1.0,
        "support": 20.0
    },
    "10": {
        "precision": 1.0,
        "recall": 1.0,
        "f1-score": 1.0,
        "support": 20.0
    },
    "11": {
        "precision": 0.95,
        "recall": 0.95,
        "f1-score": 0.95,
        "support": 20.0
    },
    "12": {
        "precision": 1.0,
        "recall": 1.0,
        "f1-score": 1.0,
        "support": 20.0
    },
    "13": {
        "precision": 1.0,
        "recall": 1.0,
        "f1-score": 1.0,
        "support": 20.0
    },
    "14": {
        "precision": 1.0,
        "recall": 1.0,
        "f1-score": 1.0,
        "support": 20.0
    },
    "15": {
        "precision": 1.0,
        "recall": 1.0,
        "f1-score": 1.0,
        "support": 20.0
    },
    "16": {
        "precision": 1.0,
        "recall": 1.0,
        "f1-score": 1.0,
        "support": 20.0
    },
    "17": {
        "precision": 1.0,
        "recall": 1.0,
        "f1-score": 1.0,
        "support": 20.0
    },
    "18": {
        "precision": 1.0,
        "recall": 1.0,
        "f1-score": 1.0,
        "support": 20.0
    },
    "19": {
        "precision": 1.0,
        "recall": 1.0,
        "f1-score": 1.0,
        "support": 20.0
    },
    "20": {
        "precision": 1.0,
        "recall": 0.95,
        "f1-score": 0.9743589743589743,
        "support": 20.0
    },
    "21": {
        "precision": 1.0,
        "recall": 1.0,
        "f1-score": 1.0,
        "support": 20.0
    },
    "accuracy": 0.9929078014184397,
    "macro avg": {
        "precision": 0.9933982683982684,
        "recall": 0.993181818181818,
        "f1-score": 0.9931789754960487,
        "support": 423.0
    },
    "weighted avg": {
        "precision": 0.993132950579759,
        "recall": 0.9929078014184397,
        "f1-score": 0.9929048444876156,
        "support": 423.0
    }
}